{
  "string": [
    {
      "name": "page_show",
      "value": "page from package"
    },
    {
      "name": "EntryAbility_desc",
      "value": "description"
    },
    {
      "name": "EntryAbility_label",
      "value": "label"
    },
    {
      "name": "custom_tab_home",
      "value": "首页"
    },
    {
      "name": "custom_tab_tendency",
      "value": "趋势"
    },
    {
      "name": "custom_tab_carbonFriendCircle",
      "value": "碳友圈"
    },
    {
      "name": "custom_tab_mine",
      "value": "我的"
    },
    {
      "name": "carbonFootprintTitle",
      "value": "碳足迹"
    },
    {
      "name": "recordTitle",
      "value": "碳行记录"
    },
    {
      "name": "recordContent",
      "value": "绿色节能足迹"
    },
    {
      "name": "taskTitle",
      "value": "减碳任务"
    },
    {
      "name": "taskContent",
      "value": "参与获得积分"
    }
  ]
}
